exceltosqlserver/__init__.py
exceltosqlserver/_api.py
exceltosqlserver/exceltosqlserver.py
exceltosqlserver/test_data/__init__.py
exceltosqlserver/test_data/test01.xls
exceltosqlserver-0.2.5.dist-info/LICENSE
exceltosqlserver-0.2.5.dist-info/METADATA
exceltosqlserver-0.2.5.dist-info/WHEEL
exceltosqlserver-0.2.5.dist-info/top_level.txt
exceltosqlserver-0.2.5.dist-info/RECORD
