Metadata-Version: 2.1
Name: exceltosqlserver
Version: 0.2.5
Summary: This package help convert your excel files (xlsx,xls,csv) to SQL Server Database.
Home-page: https://github.com/Xiangyongluo/exceltosqlserver
Author: Xiangyong Luo
Author-email: rochemay@163.com
Classifier: Programming Language :: Python :: 3
Classifier: License :: OSI Approved :: MIT License
Classifier: Operating System :: OS Independent
Requires-Python: >=3.10
License-File: LICENSE
